baro/__init__.py
baro/_bocpd.py
baro/anomaly_detection.py
baro/reproducibility.py
baro/root_cause_analysis.py
baro/utility.py
fse_baro-0.2.2.dist-info/licenses/LICENSE
fse_baro-0.2.2.dist-info/METADATA
fse_baro-0.2.2.dist-info/WHEEL
fse_baro-0.2.2.dist-info/top_level.txt
fse_baro-0.2.2.dist-info/RECORD
