Metadata-Version: 2.4
Name: fse-baro
Version: 0.2.2
Summary: BARO: Robust Root Cause Analysis for Microservices via Multivariate Bayesian Online Change Point Detection
Author-email: Luan Pham <phamquiluan@gmail.com>
License: MIT License
Project-URL: Homepage, https://github.com/phamquiluan/baro/
Project-URL: Issues, https://github.com/phamquiluan/baro/issues
License-File: LICENSE
Requires-Dist: numpy
Requires-Dist: pandas
Requires-Dist: scikit-learn
Requires-Dist: pytest
Requires-Dist: tqdm
Requires-Dist: requests
Requires-Dist: matplotlib
Dynamic: license-file
